mages/__init__.py
mages/_nbdev.py
mages/characters.py
mages/cli.py
mages/game.py
mages-0.0.8.dist-info/LICENSE
mages-0.0.8.dist-info/METADATA
mages-0.0.8.dist-info/WHEEL
mages-0.0.8.dist-info/entry_points.txt
mages-0.0.8.dist-info/top_level.txt
mages-0.0.8.dist-info/RECORD
