Metadata-Version: 2.1
Name: mages
Version: 0.0.8
Summary: Cute little python module full of magic and wonder
Home-page: https://github.com/ncoop57/mages/tree/master/
Author: Nathan Cooper
Author-email: nathanallencooper@gmail.com
License: Apache Software License 2.0
Keywords: text-based text game magic mages
Platform: UNKNOWN
Classifier: Development Status :: 3 - Alpha
Classifier: Intended Audience :: End Users/Desktop
Classifier: License :: OSI Approved :: Apache Software License
Classifier: Natural Language :: English
Classifier: Programming Language :: Python :: 3.6
Classifier: Programming Language :: Python :: 3.7
Classifier: Programming Language :: Python :: 3.8
Requires-Python: >=3.6
Requires-Dist: fastcore (==1.3.16)
